setup.py
src/auto_scaling/__init__.py
src/auto_scaling/bcs.py
src/auto_scaling/config.py
src/auto_scaling/const.py
src/auto_scaling/deadline.py
src/auto_scaling/linux_loader.py
src/auto_scaling/main.py
src/auto_scaling/monitor.py
src/auto_scaling/version.py
src/auto_scaling/windows_loader.py
src/auto_scaling/Deadline/Balancer.py
src/auto_scaling/Deadline/ConnectionProperty.py
src/auto_scaling/Deadline/DeadlineConnect.py
src/auto_scaling/Deadline/DeadlineSend.py
src/auto_scaling/Deadline/DeadlineUtility.py
src/auto_scaling/Deadline/Groups.py
src/auto_scaling/Deadline/JobReports.py
src/auto_scaling/Deadline/JobTaskLimit.py
src/auto_scaling/Deadline/Jobs.py
src/auto_scaling/Deadline/Limits.py
src/auto_scaling/Deadline/MappedPaths.py
src/auto_scaling/Deadline/MaximumPriority.py
src/auto_scaling/Deadline/Plugins.py
src/auto_scaling/Deadline/Pools.py
src/auto_scaling/Deadline/ProxyServer.py
src/auto_scaling/Deadline/Pulse.py
src/auto_scaling/Deadline/Repository.py
src/auto_scaling/Deadline/Slaves.py
src/auto_scaling/Deadline/SlavesRenderingJob.py
src/auto_scaling/Deadline/TaskReports.py
src/auto_scaling/Deadline/Tasks.py
src/auto_scaling/Deadline/Users.py
src/auto_scaling/Deadline/__init__.py
src/auto_scaling/conf/__init__.py
src/auto_scaling/conf/config.ini
src/batchcompute_auto_scaling.egg-info/PKG-INFO
src/batchcompute_auto_scaling.egg-info/SOURCES.txt
src/batchcompute_auto_scaling.egg-info/dependency_links.txt
src/batchcompute_auto_scaling.egg-info/entry_points.txt
src/batchcompute_auto_scaling.egg-info/requires.txt
src/batchcompute_auto_scaling.egg-info/top_level.txt