Metadata-Version: 1.0
Name: batchcompute-auto-scaling
Version: 0.0.1
Summary: Aliyun batchcompute auto scaling for deadline
Home-page: http://www.aliyun.com/product/batchcompute
Author: lingjiu
Author-email: lingjiu.hlz@alibaba-inc.com
License: MIT License
Keywords: batchcompute-auto-scaling,batchcompute,autoscaling,deadline
Platform: any
